opyrators/__init__.py
opyrators/fermions.py
opyrators/spins.py
tests/__init__.py
tests/test_fermions.py
opyrators-1.0.0.dist-info/LICENSE
opyrators-1.0.0.dist-info/METADATA
opyrators-1.0.0.dist-info/WHEEL
opyrators-1.0.0.dist-info/top_level.txt
opyrators-1.0.0.dist-info/RECORD
