Metadata-Version: 2.1
Name: opyrators
Version: 1.0.0
Summary: Manipulate quantum many-body operators
Home-page: https://github.com/everthemore/opyrators
Author: Evert van Nieuwenburg
Author-email: evert.v.nieuwenburg@gmail.com
License: UNKNOWN
Platform: UNKNOWN
Classifier: Programming Language :: Python :: 2
Classifier: Programming Language :: Python :: 3
Classifier: Development Status :: 4 - Beta
Classifier: License :: OSI Approved :: MIT License
Classifier: Operating System :: OS Independent
Requires-Python: >=2.7
Requires-Dist: numpy
